revjson/__init__.py
revjson/revjson.py
revjson-0.1.0.dist-info/LICENSE
revjson-0.1.0.dist-info/WHEEL
revjson-0.1.0.dist-info/METADATA
revjson-0.1.0.dist-info/RECORD
