Metadata-Version: 2.1
Name: revjson
Version: 0.1.0
Summary: A Python library for intuitive JSON handling
License: MIT
Author: reeve0930
Author-email: reeve0930@gmail.com
Requires-Python: >=3.8,<4.0
Classifier: License :: OSI Approved :: MIT License
Classifier: Programming Language :: Python :: 3
Classifier: Programming Language :: Python :: 3.8
Classifier: Programming Language :: Python :: 3.9
